sik_stochastic_tests/__init__.py
sik_stochastic_tests/decorator.py
sik_stochastic_tests/plugin.py
sik_stochastic_tests-0.1.3.dist-info/METADATA
sik_stochastic_tests-0.1.3.dist-info/WHEEL
sik_stochastic_tests-0.1.3.dist-info/entry_points.txt
sik_stochastic_tests-0.1.3.dist-info/licenses/LICENSE
sik_stochastic_tests-0.1.3.dist-info/RECORD
