Metadata-Version: 2.4
Name: sik-stochastic-tests
Version: 0.1.3
Summary: A pytest plugin for testing stochastic systems like LLMs, providing statistical confidence through multiple test runs.
License-File: LICENSE
Requires-Python: >=3.11
Requires-Dist: nest-asyncio>=1.6.0
Requires-Dist: pytest-asyncio>=0.25.3
Requires-Dist: pytest>=8.3.4
